llama_index/llms/yi/__init__.py
llama_index/llms/yi/base.py
llama_index_llms_yi-0.4.2.dist-info/METADATA
llama_index_llms_yi-0.4.2.dist-info/WHEEL
llama_index_llms_yi-0.4.2.dist-info/licenses/LICENSE
llama_index_llms_yi-0.4.2.dist-info/RECORD
